{
  "denom_raw": 0.7414781816278037,
  "R": {
    "perturbed_x1.15": 0.9646,
    "twin_folklore": 0.0,
    "negador_agnostico": 0.1929,
    "null": -0.5133
  },
  "record_corr": 0.589,
  "record_slope_pooled": 1.641,
  "record_slope_within_time": 0.34,
  "robots": {
    "terco": {
      "mean_R": 0.004590833564714558,
      "std_R": 0.0076852699641279405,
      "per_seed": [
        0.0005,
        0.0,
        0.0026,
        0.0,
        0.0198
      ]
    },
    "cuidadoso": {
      "mean_R": 0.959822180793668,
      "std_R": 0.009847506393599529,
      "per_seed": [
        0.9696,
        0.9694,
        0.9431,
        0.9559,
        0.9611
      ]
    }
  },
  "reject_do_grade8_h5": {
    "truth": 0.0993,
    "twin_folklore": 0.049
  },
  "battery_k": 11,
  "certified_load": [
    "prior_reliability=0",
    "confounding_por_era",
    "vicio:primera-hipotesis"
  ],
  "gates": {
    "seduction_band": true,
    "cheap_escape_exists": true,
    "no_inversions": true,
    "null_floor": true,
    "anticinico_bajo": true,
    "terco_twin_identity": true,
    "cuidadoso_reaches": true,
    "all": true
  }
}
